power_network_model/Horton_Plotter.py
power_network_model/__init__.py
power_network_model/Data/Horton_Connection_Info.csv
power_network_model/Data/Horton_Trafo_Info.csv
power_network_model-0.5.dist-info/DESCRIPTION.rst
power_network_model-0.5.dist-info/METADATA
power_network_model-0.5.dist-info/RECORD
power_network_model-0.5.dist-info/WHEEL
power_network_model-0.5.dist-info/metadata.json
power_network_model-0.5.dist-info/top_level.txt
