Metadata-Version: 2.0
Name: power-network-model
Version: 0.5
Summary: Python module to generate power network model for GIC calculations.
Home-page: https://github.com/TerminusEst/Power_Network
Author: Sean Blake
Author-email: blakese@tcd.ie
License: MIT
Keywords: geomagnetic space weather GICs
Platform: UNKNOWN
